jshloadoffline
