Metadata-Version: 1.1
Name: jshloadoffline
Version: 0.1.3
Summary: Load offline prefetched data in JSH
Home-page: https://github.com/lixxu/jshloadoffline
Author: Lix Xu
Author-email: xuzenglin@gmail.com
License: BSD
Platform: any
Classifier: Environment :: Web Environment
Classifier: Intended Audience :: Developers
Classifier: License :: OSI Approved :: BSD License
Classifier: Operating System :: OS Independent
Classifier: Programming Language :: Python
Classifier: Topic :: Internet :: WWW/HTTP :: Dynamic Content
Classifier: Topic :: Software Development :: Libraries :: Python Modules
